anexia_monitoring/__init__.py
anexia_monitoring/core.py
anexia_monitoring/decorators.py
anexia_monitoring/events.py
anexia_monitoring/urls.py
anexia_monitoring/views.py
anexia_monitoring/management/__init__.py
anexia_monitoring/management/commands/__init__.py
anexia_monitoring/management/commands/anxmonitormodules.py
django_anexia_monitoring-1.7.0.dist-info/LICENSE
django_anexia_monitoring-1.7.0.dist-info/METADATA
django_anexia_monitoring-1.7.0.dist-info/WHEEL
django_anexia_monitoring-1.7.0.dist-info/top_level.txt
django_anexia_monitoring-1.7.0.dist-info/RECORD
