Metadata-Version: 2.1
Name: django-anexia-monitoring
Version: 1.7.0
Summary: A Django app used to monitor updates for Django and all installed python packages in the running environment. It can be also used to check if the website is alive and working correctly.
Home-page: https://github.com/anexia-it/anexia-monitoring-django
Author: Anexia
License: MIT
Platform: UNKNOWN
Classifier: License :: OSI Approved :: MIT License
Classifier: Programming Language :: Python
Classifier: Programming Language :: Python :: 3
Classifier: Programming Language :: Python :: 3.7
Classifier: Programming Language :: Python :: 3.9
Classifier: Programming Language :: Python :: 3.10
Classifier: Programming Language :: Python :: Implementation :: CPython
Classifier: Programming Language :: Python :: Implementation :: PyPy
Classifier: Intended Audience :: Developers
Classifier: Operating System :: OS Independent
Classifier: Natural Language :: English
Classifier: Topic :: Utilities
Requires-Dist: updatable>=0.7
